{
  "arguments": {
    "left": {
      "default": "None",
      "nature": [
        "continuous"
      ],
      "type": "Array",
      "description": "Left 1D data array used to calculate scalar covariance. Used only if `data` not provided."
    },
    "right": {
      "default": "None",
      "nature": [
        "continuous"
      ],
      "type": "Array",
      "description": "Right 1D data array used to calculate scalar covariance. Used only if `data` not provided."
    },
    "data": {
      "default": "None",
      "nature": [
        "continuous"
      ],
      "type": "Array",
      "description": "2D data array used to construct covariance matrix."
    }
  },
  "id": "Covariance",
  "name": "covariance",
  "options": {},
  "return": {
    "nature": [
      "continuous"
    ],
    "type": "Array"
  },
  "description": "Calculate sample covariance.\n\n If `data` argument is provided as a 2D array, calculate covariance matrix. Otherwise, `left` and `right` 1D arrays are used to calculate a single covariance."
}